doc/byoml_runtimes.json
doc/dist.README.md
waylay/__init__.py
waylay/_version.py
waylay/auth.py
waylay/auth_interactive.py
waylay/client.py
waylay/config.py
waylay/exceptions.py
waylay/py.typed
waylay/cli/__init__.py
waylay/cli/__main__.py
waylay/cli/_decorators.py
waylay/cli/configcli.py
waylay/cli/seriescli.py
waylay/cli/servicecli.py
waylay/cli/waylaycli.py
waylay/service/__init__.py
waylay/service/_base.py
waylay/service/_decorators.py
waylay/service/analytics/__init__.py
waylay/service/byoml/__init__.py
waylay/service/byoml/_decorators.py
waylay/service/byoml/_exceptions.py
waylay/service/byoml/_model_archive.py
waylay/service/byoml/_service.py
waylay/service/byoml/about.py
waylay/service/byoml/framework.py
waylay/service/byoml/model.py
waylay/service/byoml/runtime.py
waylay/service/data/__init__.py
waylay/service/data/_service.py
waylay/service/data/events.py
waylay/service/data/series.py
waylay/service/etl/__init__.py
waylay/service/etl/_service.py
waylay/service/etl/import_.py
waylay/service/queries/__init__.py
waylay/service/queries/_decorators.py
waylay/service/queries/_exceptions.py
waylay/service/queries/_service.py
waylay/service/queries/about.py
waylay/service/queries/query.py
waylay/service/queries/_util/__init__.py
waylay/service/queries/_util/df_parser.py
waylay/service/queries/_util/parse_util.py
waylay/service/resources/__init__.py
waylay/service/resources/_service.py
waylay/service/resources/resource.py
waylay/service/resources/resource_type.py
waylay/service/storage/__init__.py
waylay/service/storage/_service.py
waylay/service/storage/about.py
waylay/service/storage/bucket.py
waylay/service/storage/content.py
waylay/service/storage/object.py
waylay/service/storage/subscription.py
waylay/service/timeseries/__init__.py
waylay/service/timeseries/_service.py
waylay/service/timeseries/tool.py
waylay/service/timeseries/parser/__init__.py
waylay/service/timeseries/parser/etlfile.py
waylay/service/timeseries/parser/export_series.py
waylay_beta-0.7.3.dist-info/licenses/LICENSE.txt
waylay_beta-0.7.3.dist-info/METADATA
waylay_beta-0.7.3.dist-info/WHEEL
waylay_beta-0.7.3.dist-info/entry_points.txt
waylay_beta-0.7.3.dist-info/top_level.txt
waylay_beta-0.7.3.dist-info/RECORD
